{"cameraMode":{"drawMode":0,"name":"Shaded","section":"Shading Mode"},"sceneLighting":true,"audioPlay":false,"sceneViewState":{"m_AlwaysRefresh":false,"showFog":true,"showSkybox":true,"showFlares":true,"showImageEffects":true,"showParticleSystems":true,"showVisualEffectGraphs":true,"m_FxEnabled":true},"in2DMode":false,"pivot":{"x":2.0139331817626955,"y":4.2159104347229,"z":-1.9061639308929444},"rotation":{"x":-0.041385501623153689,"y":0.5696286559104919,"z":-0.028726961463689805,"w":-0.8204019665718079},"size":2.158841133117676,"orthographic":true}